[
    {
        "name":"نرخ رشد بازار",
        "weight":1.00},
    {
        "name":"میزان فروش صنعت",
        "weight":1.00},
    {
        "name":"تعداد شرکت‌های رقیب",
        "weight":1.00},
    {
        "name":"تعداد بخش ‌های بازار",
        "weight":1.00},
    {
        "name":"تغییر فنی در طرح محصول",
        "weight":1.00},
    {
        "name":"سود‌آوری صنعت",
        "weight":1.00},
    {
        "name":"هزینه جذب و حفظ مشتری",
        "weight":1.00},
    {
        "name":"روند فروش صنعت",
        "weight":1.00}
]